MANIFEST.in
setup.cfg
setup.py
bin/blockstack-server
bin/blockstored
blockstore/__init__.py
blockstore/blockmirrord.py
blockstore/blockstore-testset.tac
blockstore/blockstore.tac
blockstore/blockstored.py
blockstore/build_nameset.py
blockstore.egg-info/PKG-INFO
blockstore.egg-info/SOURCES.txt
blockstore.egg-info/dependency_links.txt
blockstore.egg-info/not-zip-safe
blockstore.egg-info/requires.txt
blockstore.egg-info/top_level.txt
blockstore/dht/__init__.py
blockstore/dht/plugin.py
blockstore/dht/server.tac
blockstore/dht/storage.py
blockstore/dht/test.py
blockstore/lib/__init__.py
blockstore/lib/b40.py
blockstore/lib/config.py
blockstore/lib/hashing.py
blockstore/lib/scripts.py
blockstore/lib/nameset/__init__.py
blockstore/lib/nameset/namedb.py
blockstore/lib/nameset/virtualchain_hooks.py
blockstore/lib/operations/__init__.py
blockstore/lib/operations/announce.py
blockstore/lib/operations/nameimport.py
blockstore/lib/operations/namespacepreorder.py
blockstore/lib/operations/namespaceready.py
blockstore/lib/operations/namespacereveal.py
blockstore/lib/operations/preorder.py
blockstore/lib/operations/register.py
blockstore/lib/operations/revoke.py
blockstore/lib/operations/transfer.py
blockstore/lib/operations/update.py
blockstore/tests/__init__.py
blockstore/tests/mock_bitcoind.py
blockstore/tests/mock_utxo_provider.py
blockstore/tests/run_scenario.py
blockstore/tests/unit_tests.py
blockstore/tests/scenarios/__init__.py
blockstore/tests/scenarios/name_import_transfer_update.py
blockstore/tests/scenarios/name_import_update_transfer_revoke_verify_multi.py
blockstore/tests/scenarios/name_preorder.py
blockstore/tests/scenarios/name_preorder_cantmodify.py
blockstore/tests/scenarios/name_preorder_expire.py
blockstore/tests/scenarios/name_preorder_register.py
blockstore/tests/scenarios/name_preorder_register_announce.py
blockstore/tests/scenarios/name_preorder_register_cantsteal.py
blockstore/tests/scenarios/name_preorder_register_collisions.py
blockstore/tests/scenarios/name_preorder_register_expire.py
blockstore/tests/scenarios/name_preorder_register_expire_snv.py
blockstore/tests/scenarios/name_preorder_register_nodups.py
